keepintouch/__init__.py
keepintouch/auth.py
keepintouch/utils.py
keepintouch-1.0.5.dist-info/METADATA
keepintouch-1.0.5.dist-info/WHEEL
keepintouch-1.0.5.dist-info/top_level.txt
keepintouch-1.0.5.dist-info/RECORD
