Metadata-Version: 2.1
Name: keepintouch
Version: 1.0.5
Summary: Simple Python client library for https://httpbin.cn/kit
Home-page: https://github.com/xizhendu/keepintouch-sdk-python
Author: Xizhen Du
Author-email: xizhendu@gmail.com
Requires-Dist: requests
